Histimator-0.2.1.dist-info/DESCRIPTION.rst
Histimator-0.2.1.dist-info/METADATA
Histimator-0.2.1.dist-info/RECORD
Histimator-0.2.1.dist-info/WHEEL
Histimator-0.2.1.dist-info/metadata.json
Histimator-0.2.1.dist-info/top_level.txt
histimator/__init__.py
histimator/backend.py
histimator/estimator.py
histimator/interpolation.py
histimator/models.py
histimator/optimiser.py
histimator/pdfs.py
histimator/util.py
