Metadata-Version: 2.0
Name: Histimator
Version: 0.2.1
Summary: A solution for performing maximum likelihood estimation on models built from histogram templates.
Home-page: https://github.com/Histimator/Histimator.git
Author: Yacine Haddad
Author-email: yhaddad@cern.ch
License: GNU General Public License v3
Keywords: histimator
Platform: UNKNOWN
Classifier: Development Status :: 2 - Pre-Alpha
Classifier: Intended Audience :: Developers
Classifier: License :: OSI Approved :: GNU General Public License v3 (GPLv3)
Classifier: Natural Language :: English
Classifier: Programming Language :: Python :: 2
Classifier: Programming Language :: Python :: 2.7
Classifier: Programming Language :: Python :: 3
Classifier: Programming Language :: Python :: 3.4
Classifier: Programming Language :: Python :: 3.5
Classifier: Programming Language :: Python :: 3.6
Requires-Dist: bumpversion
Requires-Dist: wheel
Requires-Dist: watchdog
Requires-Dist: flake8
Requires-Dist: tox
Requires-Dist: coverage
Requires-Dist: Sphinx
Requires-Dist: twine
Requires-Dist: cryptography
Requires-Dist: PyYAML
Requires-Dist: numpy
Requires-Dist: scipy
Requires-Dist: iminuit
Requires-Dist: probfit
